setup.py
gaepermission/__init__.py
gaepermission/base_commands.py
gaepermission/base_commands2.py
gaepermission/decorator.py
gaepermission/facade.py
gaepermission/inspector.py
gaepermission/middleware.py
gaepermission/model.py
gaepermission.egg-info/PKG-INFO
gaepermission.egg-info/SOURCES.txt
gaepermission.egg-info/dependency_links.txt
gaepermission.egg-info/not-zip-safe
gaepermission.egg-info/top_level.txt
gaepermission/facebook/__init__.py
gaepermission/facebook/commands.py
gaepermission/facebook/model.py
gaepermission/google/__init__.py
gaepermission/google/commands.py
gaepermission/passwordless/__init__.py
gaepermission/passwordless/commands.py
gaepermission/passwordless/model.py